pwnbox/__init__.py
pwnbox/__main__.py
pwnbox/pwnbox.conf
pwnbox-2.3.1.dist-info/LICENSE
pwnbox-2.3.1.dist-info/METADATA
pwnbox-2.3.1.dist-info/WHEEL
pwnbox-2.3.1.dist-info/dependency_links.txt
pwnbox-2.3.1.dist-info/entry_points.txt
pwnbox-2.3.1.dist-info/top_level.txt
pwnbox-2.3.1.dist-info/RECORD
