Metadata-Version: 2.1
Name: pwnbox
Version: 2.3.1
Summary: The CLI tool that lets you easily deploy, customize and manage PwnBox containers.
Home-page: https://github.com/deadpackets/pwnbox-cli
Author: DeadPackets (Youssef Awad)
Author-email: deadpackets@protonmail.com
License: MIT
Keywords: pwnbox,kali,container,docker,security,pentesting
Classifier: License :: OSI Approved :: MIT License
Classifier: Programming Language :: Python :: 3
Classifier: Programming Language :: Python :: 3.6
Requires-Python: >=3.6
License-File: LICENSE
Requires-Dist: cryptography (==36.0.2)
Requires-Dist: packaging (==21.3)
Requires-Dist: ssh-wait (==1.0.1)
Requires-Dist: requests (==2.28.0)
Requires-Dist: docker (==5.0.3)
Requires-Dist: rich (==12.4.4)
Requires-Dist: six (==1.16.0)
